setup.py
imhotep_pylint/__init__.py
imhotep_pylint/plugin.py
imhotep_pylint.egg-info/PKG-INFO
imhotep_pylint.egg-info/SOURCES.txt
imhotep_pylint.egg-info/dependency_links.txt
imhotep_pylint.egg-info/entry_points.txt
imhotep_pylint.egg-info/top_level.txt