Metadata-Version: 1.1
Name: imhotep-pylint
Version: 0.0.4
Summary: An imhotep plugin for pylint validation
Home-page: https://github.com/justinabrahms/imhotep_pylint
Author: Justin Abrahms
Author-email: justin@abrah.ms
License: MIT
Platform: UNKNOWN
Requires: pylint
